Workbook

Sheet Loan Portfolio
A1: ABC COMPANY — LOAN PORTFOLIO
A2: Company | B2: ABC Company
A3: Business Plan Target | B3: RWF 500,000,000 annual revenue
A4: Purpose | B4: Controlled ERIDSS financial-risk test dataset
A5: Interest Rate | B5: 9% annual
A6: Maximum Loan per Client | B6: RWF 5,000,000
A7: Maximum Repayment Term | B7: 5 years
A8: Number of Clients | B8: 50
A10: Client ID | B10: Client Name | C10: Sector | D10: Loan Amount (RWF) | E10: Annual Interest Rate | F10: Term (Years) | G10: Monthly Payment (RWF) | H10: Outstanding Balance (RWF) | I10: Repayment Status | J10: Risk Note
A11: ABC-001 | B11: Jean N. | C11: Food Services | D11: 3900000 | E11: 0.09 | F11: 1 | G11: 341060.76 | H11: 289363.67 | I11: Current | J11: Performing account
A12: ABC-002 | B12: Aline M. | C12: Professional Services | D12: 1000000 | E12: 0.09 | F12: 5 | G12: 20758.36 | H12: 686139.55 | I12: Current | J12: Performing account
A13: ABC-003 | B13: Eric K. | C13: Professional Services | D13: 4450000 | E13: 0.09 | F13: 3 | G13: 141508.81 | H13: 1915204.7 | I13: Current | J13: Performing account
A14: ABC-004 | B14: Claudine U. | C14: Transport | D14: 900000 | E14: 0.09 | F14: 1 | G14: 78706.33 | H14: 319376.71 | I14: Current | J14: Performing account
A15: ABC-005 | B15: Samuel H. | C15: Food Services | D15: 1000000 | E15: 0.09 | F15: 2 | G15: 45684.74 | H15: 170164.7 | I15: Current | J15: Performing account
A16: ABC-006 | B16: Diane A. | C16: Transport | D16: 2250000 | E16: 0.09 | F16: 4 | G16: 55991.35 | H16: 850239 | I16: 31–60 Days Late | J16: Elevated repayment concern
A17: ABC-007 | B17: Patrick R. | C17: Professional Services | D17: 1500000 | E17: 0.09 | F17: 3 | G17: 47699.6 | H17: 945384.55 | I17: Current | J17: Performing account
A18: ABC-008 | B18: Olivia T. | C18: Agriculture | D18: 2200000 | E18: 0.09 | F18: 1 | G18: 192393.25 | H18: 883920.61 | I18: Current | J18: Performing account
A19: ABC-009 | B19: Emmanuel G. | C19: Food Services | D19: 3900000 | E19: 0.09 | F19: 2 | G19: 178170.49 | H19: 3131457.2 | I19: Current | J19: Performing account
A20: ABC-010 | B20: Grace I. | C20: Transport | D20: 2200000 | E20: 0.09 | F20: 5 | G20: 45668.38 | H20: 1655162 | I20: Current | J20: Performing account
A21: ABC-011 | B21: David B. | C21: Transport | D21: 850000 | E21: 0.09 | F21: 2 | G21: 38832.03 | H21: 178821.02 | I21: Current | J21: Performing account
A22: ABC-012 | B22: Alice W. | C22: Construction | D22: 3050000 | E22: 0.09 | F22: 3 | G22: 96989.18 | H22: 2715812.3 | I22: Current | J22: Performing account
... A60: ABC-050 | B60: Estelle K. | C60: Professional Services | D60: 3300000 | E60: 0.09 | F60: 5 | G60: 68502.57 | H60: 2844211.1 | I60: 1–30 Days Late | J60: Early delinquency; monitor
A63: PORTFOLIO SUMMARY
A64: Total Principal | B64: =SUM(D11:D60)
A65: Average Loan | B65: =AVERAGE(D11:D60)
A66: Maximum Loan | B66: =MAX(D11:D60)
A67: Total Outstanding | B67: =SUM(H11:H60)
A68: Current Accounts | B68: =COUNTIF(I11:I60,"Current")
A69: Accounts 1–30 Days Late | B69: =COUNTIF(I11:I60,"1–30 Days Late")
A70: Accounts 31–60 Days Late | B70: =COUNTIF(I11:I60,"31–60 Days Late")
A71: Accounts 61–90 Days Late | B71: =COUNTIF(I11:I60,"61–90 Days Late")
A72: Restructured Accounts | B72: =COUNTIF(I11:I60,"Restructured")

Sheet Business Plan
A1: ABC COMPANY — BUSINESS PLAN SNAPSHOT
A2: Target annual revenue | B2: 500000000 | D2: Management Notes
A3: Current projected annual revenue | B3: 410000000 | D3: ABC Company plans to reach RWF 500M in annual revenue.
A4: Revenue gap | B4: =B2-B3 | D4: The portfolio contains 50 client accounts.
A5: Loan portfolio principal | B5: ='Loan Portfolio'!B64 | D5: All loans use 9% annual interest.
A6: Portfolio / 500M target | B6: =B5/B2 | D6: No individual loan exceeds RWF 5M.
A7: Annual interest rate | B7: 0.09 | D7: No loan term exceeds 5 years.
A8: Number of borrowers | B8: 50 | D8: A small number of delinquent/restructured accounts are included intentionally for risk testing.

Sheet Risk Indicators
A1: RISK-RELEVANT PORTFOLIO INDICATORS
A3: Indicator | B3: Value | C3: Why It Matters
A4: Portfolio size | B4: ='Loan Portfolio'!B64 | C4: Total credit exposure.
A5: Average loan | B5: ='Loan Portfolio'!B65 | C5: Typical borrower exposure.
A6: Maximum individual loan | B6: ='Loan Portfolio'!B66 | C6: Tests the RWF 5M limit.
A7: Outstanding balance | B7: ='Loan Portfolio'!B67 | C7: Remaining portfolio exposure.
A8: Current accounts | B8: ='Loan Portfolio'!B68 | C8: Performing accounts.
A9: 1–30 days late | B9: ='Loan Portfolio'!B69 | C9: Early delinquency signal.
A10: 31–60 days late | B10: ='Loan Portfolio'!B70 | C10: Moderate delinquency signal.
A11: 61–90 days late | B11: ='Loan Portfolio'!B71 | C11: High delinquency signal.
A12: Restructured accounts | B12: ='Loan Portfolio'!B72 | C12: Special monitoring signal.
